imgcode/__init__.py
imgcode-0.1.dist-info/LICENCE.txt
imgcode-0.1.dist-info/METADATA
imgcode-0.1.dist-info/WHEEL
imgcode-0.1.dist-info/top_level.txt
imgcode-0.1.dist-info/RECORD
