Metadata-Version: 2.1
Name: imgcode
Version: 0.1
Summary: A simple package for Image & Video Analytics Practical
Author: Alb Tech
Author-email: albtech.in@gmail.com
Classifier: Programming Language :: Python :: 3
Classifier: License :: OSI Approved :: MIT License
Classifier: Operating System :: OS Independent
Requires-Python: >=3.6
License-File: LICENCE.txt
